xontrib/sh.py
xontrib_sh-0.3.2.dist-info/licenses/LICENSE
xontrib_sh-0.3.2.dist-info/METADATA
xontrib_sh-0.3.2.dist-info/WHEEL
xontrib_sh-0.3.2.dist-info/top_level.txt
xontrib_sh-0.3.2.dist-info/RECORD
