Metadata-Version: 2.4
Name: xontrib-sh
Version: 0.3.2
Summary: Paste and run commands from bash, zsh, fish, tcsh, pwsh, cmd in xonsh shell.
Home-page: https://github.com/anki-code/xontrib-sh
Author: anki
Author-email: author@example.com
License: BSD
Project-URL: Documentation, https://github.com/anki-code/xontrib-sh/blob/master/README.md
Project-URL: Code, https://github.com/anki-code/xontrib-sh
Project-URL: Issue tracker, https://github.com/anki-code/xontrib-sh/issues
Platform: any
Classifier: Environment :: Console
Classifier: Intended Audience :: End Users/Desktop
Classifier: Operating System :: OS Independent
Classifier: Programming Language :: Python
Classifier: Programming Language :: Unix Shell
Classifier: Topic :: System :: Shells
Classifier: Topic :: System :: System Shells
Classifier: Topic :: Terminals
Classifier: Topic :: System :: Networking
Classifier: License :: OSI Approved :: BSD License
Requires-Python: >=3.6
License-File: LICENSE
Dynamic: author
Dynamic: author-email
Dynamic: classifier
Dynamic: description
Dynamic: description-content-type
Dynamic: home-page
Dynamic: license
Dynamic: license-file
Dynamic: platform
Dynamic: project-url
Dynamic: requires-python
Dynamic: summary
